{
  "organization" : "com.nicta",
  "name" : "scoobi",
  "version" : "0.7.0",
  "description" : "scoobi",
  "site" : "",
  "tags" : [ ],
  "docs" : "",
  "resolvers" : [ "https://oss.sonatype.org/content/repositories/releases" ],
  "dependencies" : [ {
    "organization" : "org.apache.hadoop",
    "name" : "hadoop-client",
    "version" : "2.0.0-mr1-cdh4.0.1"
  }, {
    "organization" : "org.apache.hadoop",
    "name" : "hadoop-core",
    "version" : "2.0.0-mr1-cdh4.0.1"
  }, {
    "organization" : "javassist",
    "name" : "javassist",
    "version" : "3.12.1.GA"
  }, {
    "organization" : "org.apache.avro",
    "name" : "avro-mapred",
    "version" : "1.7.3.1"
  }, {
    "organization" : "org.apache.avro",
    "name" : "avro",
    "version" : "1.7.3.1"
  }, {
    "organization" : "com.thoughtworks.xstream",
    "name" : "xstream",
    "version" : "1.4.3"
  }, {
    "organization" : "com.googlecode.kiama",
    "name" : "kiama",
    "version" : "1.4.0"
  }, {
    "organization" : "com.github.mdr",
    "name" : "ascii-graphs",
    "version" : "0.0.2"
  }, {
    "organization" : "org.scalaz",
    "name" : "scalaz-core",
    "version" : "7.0.0-M7"
  }, {
    "organization" : "org.scalaz",
    "name" : "scalaz-concurrent",
    "version" : "7.0.0-M7"
  }, {
    "organization" : "org.specs2",
    "name" : "specs2",
    "version" : "1.12.3"
  }, {
    "organization" : "com.chuusai",
    "name" : "shapeless",
    "version" : "1.2.2"
  }, {
    "organization" : "org.mockito",
    "name" : "mockito-all",
    "version" : "1.9.0"
  } ],
  "scalas" : [ "2.9.2" ],
  "licenses" : [ ],
  "sbt" : false
}